{"Country Name": "Republic of Cameroon", "Capital City": ["Yaound\u00e9", {"latitude": "3 Deg 52 Min N", "longitude": "11 Deg 31 Min E"}], "Capital": {}, "Largest City": "Yaound\u00e9", "Largest city": {}, "Official languages": "English, \u2022, French", "Recognised regional languages": "Cameroonian Pidgin English, ,, Fula, ,, Ewondo, ,, Camfranglais", "Ethnic groups": "31%, Cameroon Highlanders, 19%, Equatorial Bantu, 11%, Kirdi, 10%, Fulani, 8%, Northwestern Bantu, 7% Eastern Nigritic, 13% other African, <1% non-African", "Religion, (2018), [1]": "70.7%, Christianity, 24.4%, Islam, 2.2%, Traditional faiths, 2.2%, None, 0.5% Others", "Demonym(s)": "Cameroonian", "Government": {"Government": "Unitary, dominant-party, semi-presidential, constitutional republic", "President": "Paul Biya", "Prime Minister": "Joseph Ngute"}, "Legislature": {"Legislature": "Parliament", "Upper house": "Senate", "Lower house": "National Assembly"}, "Independence, .mw-parser-output .nobold{font-weight:normal}, from, France": {"Declared": "1 January 1960", "Union with the former  British Cameroons": "1 October 1961"}, "Area": {"Total": "475,442 km, 2, (183,569 sq mi) (, 53rd, )", "Water (%)": "0.57"}, "Population": {"2020 estimate": "26,545,864, [2], (, 51st, )", "2005 census": "17,463,836, [3]", "Density": "39.7/km, 2, (102.8/sq mi) (, 167th, )"}, "GDP, (, PPP, )": {"GDP, (, PPP, )": "2018 estimate", "Total": "$95.068 billion, [4], (, 93rd, )", "Per capita": "$3,820, [4], (, 152nd, )"}, "GDP, (nominal)": {"GDP, (nominal)": "2018 estimate", "Total": "$38.445 billion, [4], (, 98th, )", "Per capita": "$1,544, [4], (, 152nd, )"}, "Gini, (2014)": "46.6, [5], high", "HDI, (2019)": "0.563, [6], medium,  , 153rd", "Currency": "Central African CFA franc, (, XAF, )", "Time zone": "UTC, +1, (, WAT, )", "Driving side": "right", "Calling code": "+237", "ISO 3166 code": "CM"}