{"Country Name": "Republic of Kenya", "Capital City": ["Nairobi", {"latitude": "1 Deg 16 Min S", "longitude": "36 Deg 48 Min E"}], "Largest City": "Nairobi", "Capital, and largest city": {}, "Official languages": "English, Swahili, [1]", "National language": "Swahili, [1]", "Ethnic groups, (2019, [2], )": "17.13%, Kikuyu, 14.35%, Luhya, 13.37%, Kalenjin, 10.65%, Luo, 9.81%, Kamba, 5.85%, Somalis, 5.68%, Kisii, 5.23%, Mijikenda, 4.15%, Meru, 13.78% Other", "Religion, (2019, [2], )": "85.5%, Christianity, \u201460.8%, Protestantism, \u201420.6%, Catholicism, \u20144.1% Other, Christian, 10.9%, Islam, 1.6%, No religion, 0.7%, Traditional faiths, 1.3%, Others", "Demonym(s)": "Kenyan", "Government": {"Government": "Unitary, presidential, constitutional, republic", "President": "Uhuru Kenyatta", "Deputy President": "William Ruto", "Speaker of the Senate": "Kenneth Lusaka", "Speaker of the National Assembly": "Justin Muturi", "Chief Justice": "David Maraga", "Attorney General": "Paul Kihara Kariuki"}, "Legislature": {"Legislature": "Parliament", "Upper house": "Senate", "Lower house": "National Assembly"}, "Independence": {"United Kingdom": "12 December 1963", "Republic declared": "12 December 1964"}, "Area": {"Total": "580,367 km, 2, (224,081 sq mi), [3], [4], (, 48th, )", "Water (%)": "2.3"}, "Population": {"2019 census": "47,564,296, [5], (, 29th, )", "Density": "78/km, 2, (202.0/sq mi) (, 124th, )"}, "GDP, (, PPP, )": {"GDP, (, PPP, )": "2020 estimate", "Total": "$206.532 billion, [6]", "Per capita": "$4,071, [7]"}, "GDP, (nominal)": {"GDP, (nominal)": "2020 estimate", "Total": "$109.116 billion, [7]", "Per capita": "$2,296, [7]"}, "Gini, (2014)": "42.5, [8], medium,  , 48th", "HDI, (2019)": "0.601, [9], medium,  , 143rd", "Currency": "Kenyan shilling, (, KES, )", "Time zone": "UTC, +3, (, EAT, )", "Date format": "dd/mm/yy (, AD, )", "Driving side": "left", "Calling code": "+254", "ISO 3166 code": "KE"}