{"Country Name": "Syrian Arab Republic", "Capital City": ["Damascus", {"latitude": "33 Deg 30 Min N", "longitude": "36 Deg 18 Min E"}], "Largest City": "Damascus", "Capital, and largest city": {}, "Official languages": "Arabic, [1]", "Ethnic groups": "Syrian Arabs, Arameans, Kurds, Turkomans, Assyrians, Circassians, Armenians, Greeks", "Religion": "87%, Islam, 10%, Christianity, [2], 3%, Druzism, [3]", "Demonym(s)": "Syrian", "Government": {"Government": "Unitary, dominant-party, semi-presidential, Ba\u2019athist, republic, [4]", "President": "Bashar al-Assad", "Prime Minister": "Hussein Arnous", "Vice Presidents": "Farouk al-Sharaa, Najah al-Attar", "Speaker of the People's Council": "Hammouda Sabbagh"}, "Legislature": "People's Council", "Establishment": {"Arab Kingdom of Syria": "8 March 1920", "State of Syria  under  French mandate": "1 December 1924", "Syrian Republic": "14 May 1930", "De jure  Independence": "24 October 1945", "De facto  Independence": "17 April 1946", "United Arab Republic": "28 September 1961", "Ba'ath party  takes power": "8 March 1963", "Current constitution": "27 February 2012"}, "Area": {"Total": "185,180, [5], km, 2, (71,500 sq mi) (, 87th, )", "Water (%)": "1.1"}, "Population": {"2020 estimate": "17,500,657 (, 66th, )", "2010 census": "21,018,834", "Density": "118.3/km, 2, (306.4/sq mi) (, 70th, )"}, "GDP, (, PPP, )": {"GDP, (, PPP, )": "2015 estimate", "Total": "$50.28 billion, [6]", "Per capita": "$2,900, [6]"}, "GDP, (nominal)": {"GDP, (nominal)": "2014 estimate", "Total": "$24.6 billion, [6], (, 167, )", "Per capita": "$831, [6]"}, "Gini, (2014)": "55.8, [7], high", "HDI, (2019)": "0.567, [8], medium,  , 151st", "Currency": "Syrian pound, (, SYP, )", "Time zone": {"Time zone": "UTC, +2, (, EET, )", "DST  )": "UTC, +3, (, EEST, )"}, "Driving side": "right", "Calling code": "+963", "ISO 3166 code": "SY"}